rtvc-0.2.0.dist-info/METADATA
rtvc-0.2.0.dist-info/WHEEL
rtvc-0.2.0.dist-info/entry_points.txt
rtvc-0.2.0.dist-info/licenses/LICENSE
rtvc/__init__.py
rtvc/__main__.py
rtvc/assets/icon.png
rtvc/audio.py
rtvc/config.py
rtvc/gui.py
rtvc/i18n.py
rtvc/locales/en_US.yaml
rtvc/locales/zh_CN.yaml
rtvc/plugins/__init__.py
rtvc/plugins/base.py
rtvc/plugins/diffusion.py
rtvc/plugins/hifisinger.py
rtvc/plugins/rvc.py
rtvc-0.2.0.dist-info/RECORD
