Metadata-Version: 2.1
Name: rtvc
Version: 0.2.0
Summary: Real-Time Voice Conversion GUI
Keywords: voice-conversion svc
Author-Email: lengyue <lengyue@lengyue.me>
License: MIT
Classifier: Development Status :: 3 - Alpha
Classifier: Programming Language :: Python :: 3.10
Project-URL: Repository, https://github.com/fishaudio/realtime-vc-gui
Requires-Python: <3.12,>=3.10
Requires-Dist: noisereduce>=2.0.1
Requires-Dist: sounddevice>=0.4.6
Requires-Dist: pyyaml>=6.0
Requires-Dist: PyQt6>=6.5.0
Requires-Dist: pyqtdarktheme==2.1.0
Requires-Dist: requests>=2.31.0
Requires-Dist: librosa==0.9.2
